{
    "$schema": "https://repometric.github.io/linterhub/schema/args.json",
    "id": "xo",
    "type": "object",
    "allOf": [
        {
            "$ref": "#/definitions/options"
        }
    ],
    "definitions": {
        "arguments": {
            "type": "object",
            "properties": {
                "--init": {
                    "id": "args:--init",
                    "type": "string",
                    "description": "Add XO to your project"
                },
                "--fix": {
                    "id": "args:--fix",
                    "type": "null",
                    "description": "Automagically fix issues"
                },
                "--reporter": {
                    "type": "string",
                    "description": "Reporter to use"
                },
                "--env": {
                    "id": "args:--env",
                    "type": "array",
                    "description": "Environment preset"
                },
                "--global": {
                    "id": "args:--global",
                    "type": "array",
                    "description": "Global variable"
                },
                "--ignore": {
                    "id": "args:--ignore",
                    "type": "array",
                    "description": "Additional paths to ignore"
                },
                "--space": {
                    "id": "args:--space",
                    "type": "number",
                    "description": "Use space indent instead of tabs"
                },
                "--no-semicolon": {
                    "type": "string",
                    "description": "Prevent use of semicolons"
                },
                "--plugin": {
                    "id": "args:--plugin",
                    "type": "array",
                    "description": "Include third-party plugins"
                },
                "--extend": {
                    "id": "args:--extend",
                    "type": "array",
                    "description": "Extend defaults with a custom config"
                },
                "--open": {
                    "id": "args:--open",
                    "type": "string",
                    "description": "Open files with issues in your editor"
                },
                "--quiet": {
                    "id": "args:--quiet",
                    "type": "null",
                    "description": "Show only errors and no warnings"
                },
                "--extension": {
                    "id": "args:--extension",
                    "type": "array",
                    "description": "Additional extension to lint"
                },
                "--no-esnext": {
                    "id": "args:--no-esnext",
                    "type": "null",
                    "description": "Don't enforce ES2015+ rules"
                },
                "--cwd": {
                    "type": "string",
                    "description": "Working directory for files"
                },
                "--help": {
                    "type": "null",
                    "description": "Show help"
                },
                "--stdin-filename": {
                    "type": "string",
                    "description": "Specify a filename for the --stdin option"
                },
                "--stdin": {
                    "id": "linterhub:stdin",
                    "type": "null",
                    "description": "Lint code provided on stdin"
                },
                "": {
                    "id": "linterhub:path",
                    "type": "string",
                    "description": "Path for analysis"
                }
            }
        },
        "section": {
            "type": "object",
            "description": "The engine configuration section",
            "properties": {
                "name": {
                    "type": "string",
                    "description": "The engine name",
                    "enum": [
                        "xo"
                    ]
                },
                "options": {
                    "type": "object",
                    "description": "The engine configuration",
                    "$ref": "#/definitions/options"
                }
            }
        }
    }
}
